slashed/__init__.py
slashed/base.py
slashed/builtin/__init__.py
slashed/builtin/help_cmd.py
slashed/builtin/system.py
slashed/commands.py
slashed/completers.py
slashed/completion.py
slashed/context.py
slashed/events.py
slashed/exceptions.py
slashed/log.py
slashed/output.py
slashed/prompt_toolkit_completer.py
slashed/py.typed
slashed/registry.py
slashed/router.py
slashed/slashed_types.py
slashed/store.py
slashed/textual_adapter/__init__.py
slashed/textual_adapter/app.py
slashed/textual_adapter/command_base.py
slashed/textual_adapter/command_input.py
slashed/textual_adapter/command_textarea.py
slashed/textual_adapter/dropdown.py
slashed/textual_adapter/log.py
slashed/textual_adapter/suggester.py
slashed/utils.py
slashed-1.1.3.dist-info/licenses/LICENSE
slashed-1.1.3.dist-info/WHEEL
slashed-1.1.3.dist-info/METADATA
slashed-1.1.3.dist-info/RECORD
