Metadata-Version: 2.4
Name: slashed
Version: 1.1.3
Summary: Slash commands and autocompletions
Keywords: 
Author: Philipp Temminghoff
Author-email: Philipp Temminghoff <philipptemminghoff@googlemail.com>
License-Expression: MIT
License-File: LICENSE
Classifier: Development Status :: 4 - Beta
Classifier: Intended Audience :: Developers
Classifier: Operating System :: OS Independent
Classifier: Programming Language :: Python :: 3
Classifier: Programming Language :: Python :: 3 :: Only
Classifier: Programming Language :: Python :: 3.12
Classifier: Programming Language :: Python :: 3.13
Classifier: Programming Language :: Python :: 3.14
Classifier: Topic :: Documentation
Classifier: Topic :: Software Development
Classifier: Topic :: Utilities
Classifier: Typing :: Typed
Requires-Dist: psygnal>=0.11.1
Requires-Dist: universal-pathlib>=0.3.4
Requires-Dist: psutil>=6.1.1 ; extra == 'system-commands'
Requires-Python: >=3.13
Project-URL: Code coverage, https://app.codecov.io/gh/phil65/slashed
Project-URL: Discussions, https://github.com/phil65/slashed/discussions
Project-URL: Documentation, https://phil65.github.io/slashed/
Project-URL: Issues, https://github.com/phil65/slashed/issues
Project-URL: Source, https://github.com/phil65/slashed
Provides-Extra: system-commands
